last_watched_series/__init__.py
last_watched_series/main.py
last_watched_series/tests/__init__.py
last_watched_series-1.0.0.dist-info/LICENSE
last_watched_series-1.0.0.dist-info/METADATA
last_watched_series-1.0.0.dist-info/WHEEL
last_watched_series-1.0.0.dist-info/entry_points.txt
last_watched_series-1.0.0.dist-info/top_level.txt
last_watched_series-1.0.0.dist-info/RECORD
