Metadata-Version: 2.1
Name: last-watched-series
Version: 1.0.0
Summary: A simple commandline application to memorizing the last watched series
Home-page: https://github.com/Qyutou/last_watched_series
Author: Qyutou
Author-email: qyutou@gmail.com
License: MIT
Platform: UNKNOWN
Requires-Dist: click
Requires-Dist: pandas
Requires-Dist: pathlib
